source_salesforce/__init__.py
source_salesforce/api.py
source_salesforce/availability_strategy.py
source_salesforce/exceptions.py
source_salesforce/rate_limiting.py
source_salesforce/run.py
source_salesforce/schemas/Describe.json
source_salesforce/source.py
source_salesforce/spec.yaml
source_salesforce/streams.py
source_salesforce/utils.py
airbyte_source_salesforce-2.7.15.dist-info/METADATA
airbyte_source_salesforce-2.7.15.dist-info/WHEEL
airbyte_source_salesforce-2.7.15.dist-info/entry_points.txt
airbyte_source_salesforce-2.7.15.dist-info/RECORD
