Metadata-Version: 2.1
Name: airbyte-source-salesforce
Version: 2.7.15
Summary: Source implementation for Salesforce.
Home-page: https://airbyte.com
License: ELv2
Author: Airbyte
Author-email: contact@airbyte.io
Requires-Python: >=3.10,<3.12
Classifier: License :: Other/Proprietary License
Classifier: Programming Language :: Python :: 3
Classifier: Programming Language :: Python :: 3.10
Classifier: Programming Language :: Python :: 3.11
Requires-Dist: airbyte-cdk (>=7.0.1,<8.0.0)
Requires-Dist: pendulum (>=3.0.0,<4.0.0)
Project-URL: Documentation, https://docs.airbyte.com/integrations/sources/salesforce
Project-URL: Repository, https://github.com/airbytehq/airbyte
